dft2kp-1.2.0.dist-info/licenses/LICENSE
pydft2kp/__init__.py
pydft2kp/__version.py
pydft2kp/constants.py
pydft2kp/gfactor.py
pydft2kp/irrepwrapper.py
pydft2kp/lowdin.py
pydft2kp/qe_aux.py
pydft2kp/qsymmwrapper.py
pydft2kp/rotatebasis.py
pydft2kp/util.py
dft2kp-1.2.0.dist-info/METADATA
dft2kp-1.2.0.dist-info/WHEEL
dft2kp-1.2.0.dist-info/top_level.txt
dft2kp-1.2.0.dist-info/RECORD
