Metadata-Version: 2.4
Name: dft2kp
Version: 1.2.0
Summary: Calculates kp model and coefficients from DFT ab initio data.
Author-email: "Gerson J. Ferreira" <gersonjferreira@ufu.br>
License-Expression: GPL-3.0-or-later
Project-URL: Homepage, https://gitlab.com/dft2kp/dft2kp
Project-URL: Documentation, https://dft2kp.gitlab.io/dft2kp/
Project-URL: Changelog, https://gitlab.com/dft2kp/dft2kp/-/blob/main/CHANGELOG.md
Requires-Python: >=3.9
License-File: LICENSE
Requires-Dist: numpy
Requires-Dist: scipy
Requires-Dist: sympy
Requires-Dist: tabulate
Requires-Dist: qsymm
Requires-Dist: matplotlib
Requires-Dist: irrep>=2.3.1
Requires-Dist: irreptables
Dynamic: license-file
